orionis/__init__.py
orionis/app.py
orionis/console/__init__.py
orionis/console/kernel.py
orionis/console/args/__init__.py
orionis/console/args/argument.py
orionis/console/base/__init__.py
orionis/console/base/command.py
orionis/console/base/scheduler.py
orionis/console/base/scheduler_event_listener.py
orionis/console/commands/__init__.py
orionis/console/commands/__publisher__.py
orionis/console/commands/cache_clear.py
orionis/console/commands/help.py
orionis/console/commands/make_command.py
orionis/console/commands/make_scheduler_listener.py
orionis/console/commands/scheduler_list.py
orionis/console/commands/scheduler_work.py
orionis/console/commands/test.py
orionis/console/commands/version.py
orionis/console/contracts/__init__.py
orionis/console/contracts/base_command.py
orionis/console/contracts/base_scheduler.py
orionis/console/contracts/cli_request.py
orionis/console/contracts/command.py
orionis/console/contracts/console.py
orionis/console/contracts/dumper.py
orionis/console/contracts/event.py
orionis/console/contracts/executor.py
orionis/console/contracts/kernel.py
orionis/console/contracts/progress_bar.py
orionis/console/contracts/reactor.py
orionis/console/contracts/schedule.py
orionis/console/contracts/schedule_event_listener.py
orionis/console/core/__init__.py
orionis/console/core/reactor.py
orionis/console/debug/__init__.py
orionis/console/debug/dumper.py
orionis/console/dynamic/__init__.py
orionis/console/dynamic/progress_bar.py
orionis/console/entities/__init__.py
orionis/console/entities/command.py
orionis/console/entities/event.py
orionis/console/entities/event_job.py
orionis/console/entities/scheduler_error.py
orionis/console/entities/scheduler_event_data.py
orionis/console/entities/scheduler_paused.py
orionis/console/entities/scheduler_resumed.py
orionis/console/entities/scheduler_shutdown.py
orionis/console/entities/scheduler_started.py
orionis/console/enums/__init__.py
orionis/console/enums/actions.py
orionis/console/enums/listener.py
orionis-0.732.0.dist-info/licenses/LICENCE
orionis-0.732.0.dist-info/METADATA
orionis-0.732.0.dist-info/WHEEL
orionis-0.732.0.dist-info/top_level.txt
orionis-0.732.0.dist-info/RECORD
